zenomatic/__init__.py
zenomatic/__main__.py
zenomatic/quotes.py
zenomatic/run.py
zenomatic/tests.py
zenomatic/utils.py
zenomatic-1.0.1.dist-info/DESCRIPTION.rst
zenomatic-1.0.1.dist-info/METADATA
zenomatic-1.0.1.dist-info/RECORD
zenomatic-1.0.1.dist-info/WHEEL
zenomatic-1.0.1.dist-info/entry_points.txt
zenomatic-1.0.1.dist-info/metadata.json
zenomatic-1.0.1.dist-info/top_level.txt
