Metadata-Version: 2.0
Name: zenomatic
Version: 1.0.1
Summary: Get the Zen of Python in your Applications
Home-page: UNKNOWN
Author: Chris Maillefaud
Author-email: chris@megalus.com.br
License: UNKNOWN
Keywords: geru dev challenge python zen
Platform: UNKNOWN
Classifier: Development Status :: 4 - Beta
Classifier: Intended Audience :: Developers
Classifier: Topic :: Software Development :: Build Tools
Classifier: Programming Language :: Python :: 2.7
Classifier: Programming Language :: Python :: 3.5
Classifier: Programming Language :: Python :: 3.6
Requires-Dist: colorama
Requires-Dist: docopt
